tsvarana/__init__.py
tsvarana/__main__.py
tsvarana/classes.py
tsvarana/command.py
tsvarana/core.py
tsvarana/plot.py
tsvarana/utils.py
tsvarana-0.2.1.dist-info/LICENSE
tsvarana-0.2.1.dist-info/METADATA
tsvarana-0.2.1.dist-info/WHEEL
tsvarana-0.2.1.dist-info/top_level.txt
tsvarana-0.2.1.dist-info/RECORD
