Metadata-Version: 2.1
Name: tsvarana
Version: 0.2.1
Summary: Timeseries variance analysis for fMRI
Home-page: https://github.com/IvanAlvarez/Tsvarana
Author: Ivan Alvarez
Author-email: ivanalvarezferreira@gmail.com
Maintainer-email: ivanalvarezferreira@gmail.com
License: UNKNOWN
Platform: UNKNOWN
Classifier: Programming Language :: Python :: 3
Classifier: License :: OSI Approved :: GNU General Public License v3 (GPLv3)
Classifier: Operating System :: OS Independent
Classifier: Intended Audience :: Science/Research
Classifier: Topic :: Scientific/Engineering
Requires-Python: >=3.6
Requires-Dist: numpy (>=1.19.1)
Requires-Dist: scipy (>=1.4.1)
Requires-Dist: bokeh (>=2.0.1)
Requires-Dist: nibabel (>=3.0.2)
